{
	"Ahau": 17,
	"Amenef the Burning": 1,
	"Anomaly": 6,
	"Atab": 7,
	"Bibby Bloodbath": 16,
	"Black Knight": 9,
	"Black Vixen": 42,
	"Bloodback": 33,
	"Brother Worm": 4,
	"Bruton": 14,
	"Chikhaton": 1,
	"Count Vlarkorth": 1,
	"Crultor": 14,
	"Damage Resonance": 6,
	"Darkfang": 32,
	"Dazed Leaf Golem": 2,
	"Deadeye Devious": 3,
	"Despor": 14,
	"Dipthrah": 1,
	"Diseased Bill": 22,
	"Diseased Dan": 36,
	"Diseased Fred": 3,
	"Dragon Pack": 14,
	"Drume": 64,
	"Duke Krule": 2,
	"Earl Osam": 1,
	"elder bloodjaw": 16,
	"Eradicator": 6,
	"Ethershreck": 6,
	"Faceless Bane": 4,
	"Fleshcrawler": 1,
	"Gorga": 33,
	"Gorgo": 3,
	"Grand Canon Dominus": 14,
	"Grand Chaplain Gaunder": 10,
	"Grand Commander Soeren": 12,
	"Grand Master Oberon": 39,
	"Greedok": 14,
	"Guard Captain Quaid": 1,
	"Heoni": 35,
	"Horestis": 1,
	"Ichgahal": 1,
	"Irgix the Flimsy": 1,
	"Izcandar Champion of Summer": 1,
	"Izcandar Champion of Winter": 1,
	"Jailer": 41,
	"Katex Blood Tongue": 27,
	"Kroazur": 16,
	"Kusuma": 5,
	"Leiden": 3,
	"Lethal Lissy": 2,
	"Leviathan": 3,
	"Lizard Gate Guardian": 1,
	"Lord Azaram": 2,
	"Madareth": 1,
	"Maliz": 14,
	"Mazoran": 1,
	"Megasylvan Yselda": 2,
	"Mitmah Vanguard": 9,
	"Morik the Gladiator": 2,
	"Neferi the Spy": 1,
	"Omruc": 1,
	"Outburst": 6,
	"Phrodomo": 1,
	"Plagirath": 1,
	"Preceptor Lazare": 17,
	"Rage of Mazoran": 19,
	"Raging Mage": 1,
	"Ratmiral Blackwhiskers": 1,
	"Ravenous Hunger": 3,
	"Raxias": 4,
	"Ron the Ripper": 1,
	"Rupture": 1,
	"Scarlett Etzel": 80,
	"Shadowpelt": 33,
	"Sharpclaw": 32,
	"Sir Baeloc": 1,
	"Sir Nictros": 1,
	"Sir Valorcrest": 1,
	"Srezz Yellow Eyes": 27,
	"Stonecracker": 1,
	"Teneshpar": 4,
	"Tentugly": 3,
	"Thalas": 1,
	"Thawing Dragon Lord": 1,
	"The Big Bad One": 1,
	"The Bloodtusk": 1,
	"The Brainstealer": 3,
	"The Collector": 1,
	"The Dread Maiden": 3,
	"The End of Days": 30,
	"The Fear Feaster": 4,
	"The Flaming Orchid": 2,
	"The Many": 2,
	"The Monster": 3,
	"The Moonlight Aster": 2,
	"The Noxious Spawn": 3,
	"The Old Widow": 1,
	"The Pale Worm": 4,
	"The Snapper": 1,
	"The Unwelcome": 4,
	"The Winter Bloom": 2,
	"Timira the Many-Headed": 33,
	"Unaz the Mean": 1,
	"Urmahlullu the Weakened": 4,
	"Ushuriel": 1,
	"Utua Stone Sting": 27,
	"Vemiath": 2,
	"Vengar": 14,
	"Vilear": 14,
	"Yirkas Blue Scales": 27,
	"Zugurosh": 2,
	"abyssal calamary": 342,
	"acid blob": 276,
	"acolyte of the cult": 5860,
	"adept of the cult": 8721,
	"adult goanna": 2386,
	"adventurer": 28,
	"afflicted strider": 494,
	"agrestic chicken": 4,
	"amazon": 3721,
	"ancient lion knight": 41,
	"ancient scarab": 2958,
	"animated feather": 1135,
	"animated moohtant": 1,
	"animated skunk": 5,
	"arachnophobica": 2061,
	"arctic faun": 1,
	"armadile": 906,
	"askarak demon": 46,
	"assassin": 3301,
	"azure frog": 995,
	"badger": 2885,
	"bandit": 2943,
	"banshee": 1089,
	"barbarian bloodwalker": 1780,
	"barbarian brutetamer": 1205,
	"barbarian headsplitter": 2171,
	"barbarian skullhunter": 2068,
	"barkless devotee": 454,
	"barkless fanatic": 1188,
	"bashmu": 1372,
	"bat": 2647,
	"bear": 1727,
	"behemoth": 2053,
	"berserker chicken": 206,
	"betrayed wraith": 2442,
	"black sheep": 285,
	"black sphinx acolyte": 1105,
	"blemished spawn": 1284,
	"blightwalker": 370,
	"blood beast": 2508,
	"blood crab": 1629,
	"blood hand": 669,
	"blood priest": 639,
	"blue djinn": 347,
	"boar man": 4396,
	"boar": 1344,
	"bog frog": 490,
	"bog raider": 330,
	"bonebeast": 7794,
	"bonelord": 2815,
	"boogy": 462,
	"braindeath": 3128,
	"breach brood": 19190,
	"brimstone bug": 702,
	"broken shaper": 51,
	"bug": 1985,
	"bulltaur alchemist": 1377,
	"bulltaur brute": 1503,
	"bulltaur forgepriest": 1136,
	"burning gladiator": 878,
	"burster spectre": 4565,
	"butterfly": 165,
	"calamary": 8,
	"carniphila": 3333,
	"carnisylvan sapling": 236,
	"carnivostrich": 3215,
	"carrion worm": 1662,
	"cat": 256,
	"cave chimera": 17,
	"cave devourer": 674,
	"cave hydra": 9,
	"cave rat": 2296,
	"centipede": 1555,
	"chakoya toolshaper": 364,
	"chakoya tribewarden": 507,
	"chakoya windcaller": 384,
	"charged energy elemental": 96,
	"charger": 413,
	"charging Outburst": 24,
	"chicken": 2325,
	"choking fear": 1570,
	"clay guardian": 1693,
	"cliff strider": 469,
	"clomp": 376,
	"cobra assassin": 2624,
	"cobra scout": 1301,
	"cobra vizier": 931,
	"cobra": 3104,
	"coral frog": 812,
	"corrupt naga": 328,
	"corym charlatan": 1294,
	"corym skirmisher": 1080,
	"corym vanguard": 972,
	"crab": 1457,
	"crape man": 2093,
	"crawler": 2803,
	"crazed beggar": 905,
	"crazed summer rearguard": 7586,
	"crazed summer vanguard": 4546,
	"crazed winter rearguard": 2240,
	"crazed winter vanguard": 2173,
	"crimson frog": 990,
	"crocodile": 3297,
	"crypt defiler": 1041,
	"crypt shambler": 5147,
	"crypt warden": 1298,
	"crypt warrior": 402,
	"crystal spider": 1472,
	"crystalcrusher": 722,
	"cult believer": 4950,
	"cult enforcer": 1678,
	"cult scholar": 660,
	"cunning werepanther": 3546,
	"cursed ape": 393,
	"cyclops": 5376,
	"cyclops drone": 2993,
	"cyclops smith": 2329,
	"damaged crystal golem": 264,
	"damaged worker golem": 489,
	"dark apprentice": 1450,
	"dark carnisylvan": 199,
	"dark faun": 937,
	"dark magician": 1582,
	"dark monk": 3398,
	"dark torturer": 10237,
	"darklight matter": 2846,
	"darklight source": 1879,
	"darklight striker": 3439,
	"dawnfire asura": 7502,
	"dawnfly": 6,
	"death blob": 4148,
	"deathling scout": 1026,
	"deathling spellsinger": 564,
	"deathspawn": 2,
	"deepling elite": 3,
	"deepling guard": 735,
	"deepling master librarian": 13,
	"deepling scout": 210,
	"deepling spellsinger": 472,
	"deepling tyrant": 32,
	"deepling warrior": 299,
	"deepsea blood crab": 1237,
	"deepworm": 810,
	"deer": 744,
	"defiler": 198,
	"demon outcast": 2580,
	"demon parrot": 189,
	"demon skeleton": 7566,
	"demon": 4725,
	"depolarized crackler": 12,
	"desperate white deer": 219,
	"destroyer": 1913,
	"devourer": 3792,
	"diabolic imp": 2,
	"diamond servant replica": 134,
	"dire penguin": 1,
	"diremaw": 2758,
	"disgusting ooze": 19,
	"dog": 287,
	"domestikion": 14,
	"doom deer": 339,
	"dragolisk": 10728,
	"dragon hatchling": 1424,
	"dragon lord hatchling": 312,
	"dragon lord": 2728,
	"dragon": 4216,
	"draken abomination": 866,
	"draken elite": 538,
	"draken spellweaver": 3927,
	"draken warmaster": 3567,
	"dread intruder": 16233,
	"drillworm": 1030,
	"dromedary": 75,
	"druid familiar": 10,
	"dryad": 1159,
	"dwarf geomancer": 784,
	"dwarf guard": 1936,
	"dwarf soldier": 2848,
	"dwarf": 880,
	"dworc fleshhunter": 1558,
	"dworc venomsniper": 1572,
	"dworc voodoomaster": 1512,
	"earth elemental": 1241,
	"efreet": 201,
	"elder bonelord": 1395,
	"elder forest fury": 941,
	"elder wyrm": 1293,
	"elephant": 313,
	"elf arcanist": 2386,
	"elf scout": 5427,
	"elf": 3614,
	"emerald damselfly": 2666,
	"emerald tortoise": 1,
	"energized raging mage": 5,
	"energy elemental": 999,
	"enfeebled silencer": 4642,
	"enlightened of the cult": 5062,
	"enraged crystal golem": 1229,
	"enraged white deer": 67,
	"enslaved dwarf": 102,
	"eternal guardian": 911,
	"evil sheep": 639,
	"evil sheep lord": 46,
	"execowtioner": 198,
	"exotic bat": 10551,
	"exotic cave spider": 3407,
	"eyeless devourer": 754,
	"falcon knight": 2908,
	"falcon paladin": 1753,
	"faun": 140,
	"feral sphinx": 1634,
	"feral werecrocodile": 758,
	"feverish citizen": 2228,
	"filth toad": 213,
	"fire devil": 1378,
	"fire elemental": 9427,
	"firestarter": 7,
	"fish": 42,
	"flamingo": 212,
	"flimsy lost soul": 18935,
	"floating savant": 563,
	"flying book": 213,
	"foam stalker": 1153,
	"forest fury": 3989,
	"fox": 2121,
	"frazzlemaw": 10239,
	"freakish lost soul": 47,
	"frost dragon hatchling": 979,
	"frost dragon": 1283,
	"frost flower asura": 1188,
	"frost giantess": 494,
	"frost giant": 492,
	"frost troll": 402,
	"fury": 915,
	"gang member": 767,
	"gargoyle": 2021,
	"gazer spectre": 9233,
	"gazer": 1482,
	"ghastly dragon": 3618,
	"ghost": 4367,
	"ghoul": 8264,
	"giant spider": 1708,
	"girtablilu warrior": 1388,
	"gladiator": 1584,
	"gloom wolf": 643,
	"glooth anemone": 1476,
	"glooth bandit": 4748,
	"glooth blob": 5789,
	"glooth brigand": 4802,
	"glooth golem": 1626,
	"gnarlhound": 666,
	"goblin assassin": 104,
	"goblin leader": 15,
	"goblin scavenger": 393,
	"goblin": 1095,
	"golden servant replica": 145,
	"gore horn": 4,
	"gorerilla": 4,
	"gozzler": 389,
	"grave guard": 1,
	"grave robber": 1170,
	"gravedigger": 58,
	"greater energy elemental": 4,
	"greater fire elemental": 4,
	"green djinn": 559,
	"green frog": 492,
	"grim reaper": 5795,
	"grimeleech": 3541,
	"gryphon": 59,
	"guardian of tales": 4,
	"guzzlemaw": 2615,
	"hand of cursed fate": 1297,
	"hardened usurper archer": 19,
	"hardened usurper knight": 105,
	"hardened usurper warlock": 158,
	"harpy": 1345,
	"haunted treeling": 4819,
	"hellfire fighter": 2307,
	"hellflayer": 862,
	"hellhound": 1218,
	"hellspawn": 6885,
	"hero": 5377,
	"hibernal moth": 232,
	"hideous fungus": 5917,
	"high voltage elemental": 296,
	"honour guard": 1003,
	"hoodinion": 7,
	"horse": 741,
	"hot dog": 6,
	"hulking carnisylvan": 243,
	"hulking prehemoth": 4,
	"humongous fungus": 7729,
	"humorless fungus": 3761,
	"hunger worm": 13,
	"hunter": 3275,
	"husky": 25,
	"hyaena": 1342,
	"hydra": 2436,
	"ice golem": 1256,
	"ice witch": 826,
	"icecold book": 1142,
	"iks ahpututu": 166,
	"iks aucar": 1125,
	"iks chuka": 893,
	"iks churrascan": 873,
	"iks pututu": 820,
	"iks yapunac": 1319,
	"infected weeper": 583,
	"infernal frog": 79,
	"insane siren": 2029,
	"insect swarm": 539,
	"insectoid scout": 500,
	"insectoid worker": 1895,
	"instable breach brood": 487,
	"instable sparkion": 413,
	"iron servant replica": 304,
	"ironblight": 735,
	"island troll": 1133,
	"jellyfish": 62,
	"juggernaut": 329,
	"jungle moa": 538,
	"juvenile bashmu": 2125,
	"killer caiman": 811,
	"killer rabbit": 340,
	"knight familiar": 13,
	"kongra": 996,
	"lacewing moth": 260,
	"lamassu": 934,
	"lancer beetle": 182,
	"larva": 5127,
	"lava golem": 407,
	"lava lurker attendant": 301,
	"lava lurker": 11,
	"lavafungus": 3203,
	"lavaworm": 4000,
	"leaf golem": 1467,
	"lesser swarmer": 67,
	"lich": 743,
	"liodile": 4300,
	"lion archer": 30,
	"lion commander": 12,
	"lion knight": 181,
	"lion warlock": 133,
	"lion": 758,
	"little corym charlatan": 50,
	"lizard chosen": 412,
	"lizard dragon priest": 255,
	"lizard high guard": 988,
	"lizard legionnaire": 742,
	"lizard magistratus": 2,
	"lizard sentinel": 2038,
	"lizard snakecharmer": 1270,
	"lizard templar": 2290,
	"lizard zaogun": 317,
	"lost basher": 344,
	"lost berserker": 1248,
	"lost gnome": 10,
	"lost husher": 352,
	"lost soul": 1975,
	"lost thrower": 257,
	"lumbering carnivor": 5104,
	"mad scientist": 175,
	"mad sheep": 1,
	"magical sphere": 8,
	"Magma Bubble": 5,
	"magma crawler": 658,
	"magma crystal": 15,
	"makara": 4236,
	"mammoth": 1095,
	"manta ray": 3,
	"manticore": 1271,
	"marid": 280,
	"marsh stalker": 2424,
	"massive earth elemental": 894,
	"massive fire elemental": 1664,
	"massive water elemental": 1252,
	"meadow strider": 2,
	"mean lost soul": 5573,
	"mearidion": 18,
	"medusa": 4330,
	"mega dragon": 4554,
	"memory of a book": 8,
	"memory of a carnisylvan": 4,
	"memory of a werelion": 4,
	"memory of a yalahari": 1,
	"menacing carnivor": 2536,
	"mercury blob": 418,
	"merlkin": 587,
	"metal gargoyle": 188,
	"midnight asura": 6953,
	"midnight panther": 1,
	"minotaur amazon": 172,
	"minotaur archer": 3782,
	"minotaur cult follower": 15636,
	"minotaur cult prophet": 5470,
	"minotaur cult zealot": 3611,
	"minotaur guard": 5885,
	"minotaur hunter": 639,
	"minotaur mage": 3205,
	"minotaur": 6667,
	"mitmah scout": 783,
	"mitmah seer": 416,
	"modified gnarlhound": 15,
	"mole": 3,
	"monk": 1992,
	"mooh'tah warrior": 948,
	"moohtant": 195,
	"mountain troll": 349,
	"mummy": 3520,
	"murmillion": 44,
	"mushroom sniffer": 182,
	"mutated bat": 1617,
	"mutated human": 2525,
	"mutated rat": 1463,
	"mutated tiger": 3004,
	"naga archer": 2930,
	"naga warrior": 5288,
	"necromancer": 1963,
	"nightmare scion": 2315,
	"nightmare": 1474,
	"nightstalker": 368,
	"noble lion": 380,
	"nomad": 942,
	"northern pike": 11,
	"novice of the cult": 1967,
	"nymph": 624,
	"ogre brute": 102,
	"ogre rowdy": 704,
	"ogre ruffian": 215,
	"ogre sage": 468,
	"ogre savage": 28,
	"ogre shaman": 83,
	"omnivora": 1333,
	"orc berserker": 5246,
	"orc cult fanatic": 220,
	"orc cult inquisitor": 540,
	"orc cult minion": 491,
	"orc cult priest": 162,
	"orc cultist": 227,
	"orc leader": 3153,
	"orc marauder": 895,
	"orc rider": 1947,
	"orc shaman": 6178,
	"orc spearman": 2300,
	"orc warlord": 1889,
	"orc warrior": 3067,
	"orchid frog": 903,
	"orclops doomhauler": 4,
	"orc": 2268,
	"orewalker": 675,
	"overcharged energy element": 82,
	"overcharge": 38,
	"paladin familiar": 11,
	"panda": 674,
	"parasite": 519,
	"parder": 374,
	"parrot": 18,
	"penguin": 789,
	"phantasm": 156,
	"pigeon": 191,
	"pig": 571,
	"pirat bombardier": 3556,
	"pirat cutthroat": 10945,
	"pirat mate": 2202,
	"pirat scoundrel": 5786,
	"pirate buccaneer": 3182,
	"pirate corsair": 1752,
	"pirate cutthroat": 4441,
	"pirate ghost": 519,
	"pirate marauder": 6714,
	"pirate skeleton": 663,
	"pixie": 534,
	"plaguesmith": 2358,
	"player": 235,
	"poacher": 3136,
	"poison spider": 3159,
	"poisonous carnisylvan": 178,
	"polar bear": 1010,
	"pooka": 43,
	"priestess": 1782,
	"priestess of the wild sun": 1344,
	"putrid mummy": 3282,
	"quara constrictor scout": 1344,
	"quara constrictor": 538,
	"quara hydromancer scout": 1198,
	"quara hydromancer": 1717,
	"quara mantassin scout": 508,
	"quara mantassin": 852,
	"quara pincher scout": 1304,
	"quara pincher": 1944,
	"quara predator scout": 1560,
	"quara predator": 2655,
	"rabbit": 752,
	"rabid wolves": 506,
	"ragged rabid wolves": 115,
	"rat": 1173,
	"ravenous lava lurker": 7043,
	"reality reaver": 74,
	"reality reavers": 18333,
	"renegade knight": 4289,
	"retching horror": 953,
	"rhindeer": 2210,
	"ripper spectre": 452,
	"roaring lion": 1399,
	"rogue naga": 350,
	"rorc": 1526,
	"rot elemental": 3572,
	"rotworm": 2222,
	"rustheap golem": 1796,
	"sabretooth": 7,
	"salamander": 2206,
	"sandcrawler": 1559,
	"sandstone scorpion": 3,
	"scarab": 2652,
	"scissorion": 40,
	"scorpion": 3475,
	"sea serpent": 677,
	"seagull": 499,
	"serpent spawn": 4304,
	"servant of Tentugly": 18,
	"shaburak demon": 32,
	"shadow pupil": 967,
	"shaper matriarch": 1,
	"shark": 1201,
	"sheep": 205,
	"shock head": 964,
	"sibang": 966,
	"sight of surrender": 11,
	"silencer": 7202,
	"silver rabbit": 200,
	"skeleton elite warrior": 1160,
	"skeleton warrior": 474,
	"skeleton": 6663,
	"skunk": 197,
	"slime": 2723,
	"slug": 96,
	"smuggler": 4054,
	"snake": 3794,
	"solitary frost dragon": 2,
	"son of Verminor": 36,
	"sorcerer familiar": 8,
	"soul-broken harbinger": 4642,
	"souleater": 1612,
	"sparkion": 19261,
	"spark of destruction": 424,
	"spectre": 1290,
	"sphinx": 2542,
	"spider": 1349,
	"spiky carnivor": 5687,
	"spit nettle": 1549,
	"spitter": 16,
	"spyrat": 69,
	"squid warden": 1155,
	"squidgy slime": 1569,
	"squirrel": 2033,
	"stabilizing dread intruder": 792,
	"stabilizing reality reaver": 804,
	"stalker": 1847,
	"stampor": 40,
	"stone devourer": 409,
	"stone golem": 2061,
	"stone rhino": 460,
	"stonerefiner": 2787,
	"strange slime": 1,
	"streaked devourer": 3812,
	"swamp troll": 6933,
	"swampling": 3731,
	"swan maiden": 31,
	"swarmer": 1016,
	"symbol of fear": 23,
	"tainted soul": 275,
	"tarantula": 3127,
	"tarnished spirit": 324,
	"terramite": 693,
	"terror bird": 935,
	"thanatursus": 1313,
	"thornback tortoise": 1648,
	"tiger": 130,
	"toad": 2532,
	"tormented ghost": 16,
	"tortoise": 3387,
	"tremendous tyrant": 28,
	"troll champion": 145,
	"troll guard": 17,
	"troll-trained salamander": 204,
	"troll": 1265,
	"true dawnfire asura": 2346,
	"true frost flower asura": 421,
	"true midnight asura": 1986,
	"tunnel tyrant": 340,
	"twisted pooka": 787,
	"twisted shaper": 26,
	"two-headed turtle": 2516,
	"undead cavebear": 2,
	"undead dragon": 8,
	"undead elite gladiator": 795,
	"undead gladiator": 1632,
	"undead mine worker": 560,
	"undead prospector": 516,
	"unstable tunnel": 3,
	"usurper archer": 479,
	"usurper commander": 191,
	"usurper knight": 866,
	"usurper warlock": 294,
	"valkyrie": 2252,
	"vampire bride": 510,
	"vampire pig": 246,
	"vampire viscount": 505,
	"vampire": 2299,
	"varnished diremaw": 28,
	"venerable foam stalker": 4,
	"venerable girtablilu": 573,
	"vexclaw": 2290,
	"vicious lich": 6,
	"vicious squire": 9536,
	"vile destroyer": 4,
	"vile grandmaster": 2270,
	"vulcongra": 1042,
	"wailing widow": 146,
	"walker": 1,
	"walking pillar": 2372,
	"war golem": 250,
	"war wolf": 13405,
	"wardragon": 9881,
	"warlock": 302,
	"waspoid": 709,
	"wasp": 9451,
	"water buffalo": 14,
	"water elemental": 343,
	"weakened frazzlemaw": 6354,
	"weeper": 714,
	"werebadger": 3559,
	"werebear": 2099,
	"wereboar": 2539,
	"werecrocodile": 1515,
	"werefox": 2352,
	"werehyaena shaman": 11946,
	"werehyaena": 29275,
	"werelioness": 21365,
	"werelion": 19586,
	"werepanther": 2543,
	"weretiger": 2105,
	"werewolf": 2297,
	"white deer": 301,
	"white lion": 9561,
	"white shade": 236,
	"white tiger": 12,
	"white weretiger": 1328,
	"wiggler": 1903,
	"wild horse": 5,
	"wild warrior": 3260,
	"wilting leaf golem": 2181,
	"winter wolf": 2006,
	"wisp": 147,
	"witch": 2651,
	"wolf": 3762,
	"woodling": 20,
	"worker golem": 515,
	"worm priestess": 703,
	"wyrm": 4259,
	"wyvern": 5966,
	"yielothax": 2059,
	"young goanna": 2501,
	"young sea serpent": 475,
	"young troll": 17,
	"zombie": 1057
}
