{
	"Abyssador": 1,
	"Aftershock": 1,
	"Ahau": 16,
	"Alptramun": 2,
	"Amenef the Burning": 22,
	"Anomaly": 7,
	"Arthom the Hunter": 1,
	"Ashmunrah": 2,
	"Bibby Bloodbath": 4,
	"Black Knight": 1,
	"Black Vixen": 69,
	"Bloodback": 50,
	"Bone Capsule": 4,
	"Boogey": 3,
	"Brokul": 8,
	"Brother Chill": 1,
	"Brother Freeze": 1,
	"Brother Worm": 4,
	"Count Vlarkorth": 5,
	"Damage Resonance": 10,
	"Darkfang": 50,
	"Dazed Leaf Golem": 11,
	"Deathstrike": 1,
	"Despair": 8,
	"Dirtbeard": 3,
	"Diseased Bill": 12,
	"Diseased Dan": 13,
	"Diseased Fred": 14,
	"Doctor Perhaps": 4,
	"Dorokoll the Mystic": 2,
	"Dreadful Disruptor": 1,
	"Drume": 127,
	"Duke Krule": 5,
	"Earl Osam": 5,
	"Ekatrix": 1,
	"Eliz the Unyielding": 2,
	"Enusat the Onyx Wing": 2,
	"Eradicator": 7,
	"Eshtaba the Conjurer": 2,
	"Esmeralda": 1,
	"Essence of Malice": 2,
	"Ethershreck": 1,
	"Evil Mastermind": 3,
	"Faceless Bane": 12,
	"Foreman Kneebiter": 1,
	"Foreshock": 1,
	"Furious Scorpions": 1,
	"Ghulosh": 2,
	"Glitterscale": 1,
	"Gnomevil": 1,
	"Gorzindel": 2,
	"Goshnar's Greed": 2,
	"Goshnar's Malice": 1,
	"Goshnar's Spite": 1,
	"Grand Canon Dominus": 47,
	"Grand Chaplain Gaunder": 28,
	"Grand Commander Soeren": 53,
	"Grand Master Oberon": 105,
	"Guard Captain Quaid": 1,
	"Heoni": 27,
	"Inky": 1,
	"Irgix the Flimsy": 13,
	"Izcandar Champion of Summer": 1,
	"Izcandar Champion of Winter": 1,
	"Izcandar the Banished": 3,
	"Jailer": 123,
	"Jaul": 9,
	"Katex Blood Tongue": 48,
	"Kerberos": 3,
	"King Zelos": 3,
	"Kroazur": 26,
	"Kusuma": 26,
	"Leiden": 8,
	"Lokathmor": 2,
	"Lord Azaram": 4,
	"Mad Mage": 2,
	"Mahrdis": 2,
	"Malkhar Deathbringer": 2,
	"Man in the Cave": 1,
	"Mazzinor": 2,
	"Megasylvan Yselda": 6,
	"Mephiles": 3,
	"Mezlon the Defiler": 2,
	"Monstor": 3,
	"Morik the Gladiator": 1,
	"Mozradek": 1,
	"Mr. Punish": 1,
	"Murcion": 1,
	"Neferi the Spy": 39,
	"Omruc": 2,
	"Outburst": 7,
	"Paiz the Pauperizer": 5,
	"Plagirath": 1,
	"Preceptor Lazare": 132,
	"Pythius the Rotten": 1,
	"Ragiaz": 1,
	"Raging Mage": 1,
	"Rahemos": 1,
	"Ratmiral Blackwhiskers": 6,
	"Ravenous Hunger": 8,
	"Raxias": 5,
	"Razzagorn": 2,
	"Realityquake": 1,
	"Ribstride": 1,
	"Rupture": 2,
	"Scarlett Etzel": 222,
	"Shadowpelt": 50,
	"Sharpclaw": 49,
	"Sharptooth": 1,
	"Shulgrax": 1,
	"Sir Baeloc": 4,
	"Sir Nictros": 4,
	"Sister Hetai": 23,
	"Soul Cages": 24,
	"Splasher": 1,
	"Srezz Yellow Eyes": 49,
	"Sulphur Scuttler": 1,
	"Tarbaz": 1,
	"Tentugly": 3,
	"Thaian": 2,
	"Thawing Dragon Lord": 2,
	"The Armored Voidborn": 1,
	"The Baron From Below": 2,
	"The Blazing Rose": 1,
	"The Brainstealer": 8,
	"The Corruptor of Souls": 1,
	"The Count of the Core": 5,
	"The Dread Maiden": 4,
	"The Duke of the Depths": 2,
	"The End of Days": 66,
	"The False God": 1,
	"The Fear Feaster": 4,
	"The Flaming Orchid": 18,
	"The Lord of the Lice": 1,
	"The Many": 2,
	"The Mega Magmaoid": 1,
	"The Monster": 7,
	"The Moonlight Aster": 19,
	"The Nightmare Beast": 3,
	"The Old Widow": 1,
	"The Pale Worm": 4,
	"The Sandking": 1,
	"The Scourge of Oblivion": 1,
	"The Shatterer": 2,
	"The Sinister Hermit": 1,
	"The Souldespoiler": 1,
	"The Source of Corruption": 1,
	"The Spellstealer": 1,
	"The Unarmored Voidborn": 1,
	"The Unwelcome": 4,
	"The Winter Bloom": 20,
	"Timira the Many-Headed": 86,
	"Tyrn": 1,
	"Unaz the Mean": 13,
	"Urmahlullu the Weakened": 8,
	"Utua Stone Sting": 48,
	"Versperoth": 1,
	"Vok the Freakish": 14,
	"Yirkas Blue Scales": 48,
	"Zamulosh": 2,
	"Zanakeph": 1,
	"Zugurosh": 1,
	"abyssal calamary": 2,
	"acid blob": 119,
	"acolyte of the cult": 1436,
	"adept of the cult": 3101,
	"adult goanna": 8392,
	"adventurer": 137,
	"afflicted strider": 350,
	"agrestic chicken": 8,
	"amazon": 444,
	"ancient lion knight": 95,
	"ancient scarab": 451,
	"animated feather": 1178,
	"animated skunk": 5,
	"arachnophobica": 3336,
	"arctic faun": 2,
	"armadile": 15,
	"assassin": 37,
	"azure frog": 81,
	"badger": 381,
	"bandit": 170,
	"banshee": 121,
	"barbarian bloodwalker": 105,
	"barbarian brutetamer": 77,
	"barbarian headsplitter": 135,
	"barbarian skullhunter": 129,
	"barkless devotee": 682,
	"barkless fanatic": 622,
	"bashmu": 1080,
	"bat": 520,
	"bear": 173,
	"behemoth": 1091,
	"berserker chicken": 87,
	"betrayed wraith": 678,
	"biting book": 912,
	"black sheep": 5,
	"black sphinx acolyte": 176,
	"blemished spawn": 828,
	"blightwalker": 199,
	"bloated man-maggot": 4387,
	"blood beast": 1461,
	"blood crab": 1094,
	"blood priest": 58,
	"blue djinn": 68,
	"boar man": 3153,
	"boar": 59,
	"bog frog": 233,
	"bog raider": 174,
	"bonebeast": 1215,
	"bonelord": 117,
	"bony sea devil": 1244,
	"boogy": 51,
	"brachiodemon": 55,
	"brain squid": 5969,
	"braindeath": 16,
	"branchy crawler": 230,
	"breach brood": 4460,
	"brimstone bug": 2612,
	"broken shaper": 2,
	"bug": 265,
	"burning book": 3190,
	"burning gladiator": 563,
	"burster spectre": 2384,
	"butterfly": 82,
	"calamary": 16,
	"capricious phantom": 899,
	"carniphila": 63,
	"carnisylvan sapling": 37,
	"carnivostrich": 2337,
	"carrion worm": 96,
	"cat": 17,
	"cave chimera": 6,
	"cave devourer": 1030,
	"cave hydra": 57,
	"cave rat": 323,
	"centipede": 297,
	"charger": 429,
	"charging Outburst": 27,
	"chasm spawn": 157,
	"chicken": 92,
	"choking fear": 1271,
	"clay guardian": 1233,
	"cliff strider": 9,
	"cloak of terror": 4395,
	"clomp": 1095,
	"cobra assassin": 5190,
	"cobra scout": 3079,
	"cobra vizier": 1092,
	"cobra": 631,
	"containment crystal": 2,
	"containment machine": 1,
	"control tower": 1,
	"converter": 906,
	"coral frog": 71,
	"corrupt naga": 224,
	"corym charlatan": 828,
	"corym skirmisher": 960,
	"corym vanguard": 465,
	"courage leech": 2416,
	"crab": 463,
	"crape man": 2459,
	"crawler": 661,
	"crazed beggar": 20,
	"crazed summer rearguard": 3684,
	"crazed summer vanguard": 3331,
	"crazed winter rearguard": 1015,
	"crazed winter vanguard": 1120,
	"crimson frog": 88,
	"crocodile": 907,
	"crypt defiler": 11,
	"crypt shambler": 886,
	"crypt warden": 1945,
	"crypt warrior": 17,
	"crystal spider": 383,
	"crystal wolf": 11,
	"crystalcrusher": 341,
	"cult believer": 84,
	"cult enforcer": 15,
	"cult scholar": 7,
	"cunning werepanther": 3189,
	"cursed ape": 101,
	"cursed prospector": 95,
	"cyclops": 481,
	"cyclops drone": 22,
	"cyclops smith": 10,
	"damaged worker golem": 12,
	"damned soul": 14,
	"dark apprentice": 706,
	"dark carnisylvan": 306,
	"dark faun": 182,
	"dark magician": 578,
	"dark monk": 21,
	"dark soul reaper": 8,
	"dark soul": 68,
	"dark torturer": 6308,
	"darklight construct": 568,
	"darklight emitter": 1052,
	"darklight matter": 2639,
	"darklight source": 1660,
	"darklight striker": 3098,
	"dawnfire asura": 9167,
	"dawnfly": 78,
	"death blob": 1942,
	"death dragon": 57,
	"deathling scout": 237,
	"deathling spellsinger": 120,
	"deepling elite": 19,
	"deepling guard": 624,
	"deepling master librarian": 56,
	"deepling scout": 216,
	"deepling spellsinger": 964,
	"deepling tyrant": 43,
	"deepling warrior": 760,
	"deepling worker": 311,
	"deepsea blood crab": 6,
	"deepworm": 2381,
	"deer": 174,
	"defiler": 184,
	"demon outcast": 1680,
	"demon parrot": 9,
	"demon skeleton": 894,
	"demon": 2954,
	"depolarized crackler": 24,
	"desperate white deer": 3,
	"destroyer": 1364,
	"devourer": 1527,
	"diamond servant": 116,
	"diremaw": 4597,
	"disgusting ooze": 36,
	"distorted phantom": 269,
	"dog": 56,
	"domestikion": 58,
	"doom deer": 17,
	"dragon hatchling": 339,
	"dragon lord hatchling": 127,
	"dragon lord": 340,
	"dragon": 595,
	"draken abomination": 560,
	"draken elite": 478,
	"draken spellweaver": 2118,
	"draken warmaster": 2573,
	"dread intruder": 3835,
	"dread minion": 43,
	"drillworm": 196,
	"dromedary": 70,
	"druid familiar": 7,
	"druid's apparition": 130,
	"dwarf geomancer": 12,
	"dwarf guard": 199,
	"dwarf henchman": 38,
	"dwarf soldier": 495,
	"dwarf": 479,
	"dworc fleshhunter": 421,
	"dworc venomsniper": 402,
	"dworc voodoomaster": 161,
	"earth elemental": 154,
	"efreet": 12,
	"elder bonelord": 35,
	"elder forest fury": 14,
	"elder wyrm": 135,
	"elephant": 36,
	"elf arcanist": 363,
	"elf scout": 987,
	"elf": 744,
	"emerald damselfly": 6283,
	"energetic book": 4983,
	"energized raging mage": 18,
	"energuardian of tales": 3460,
	"energy elemental": 507,
	"enfeebled silencer": 2336,
	"enlightened of the cult": 1964,
	"enraged bookworm": 4,
	"enraged crystal golem": 102,
	"enraged sand brood": 4,
	"enraged squirrel": 1,
	"enraged white deer": 1,
	"eruption of destruction": 52,
	"eternal guardian": 2759,
	"evil sheep": 31,
	"evil sheep lord": 5,
	"execowtioner": 25,
	"exotic bat": 2479,
	"exotic cave spider": 1056,
	"eyeless devourer": 563,
	"falcon knight": 1165,
	"falcon paladin": 779,
	"faun": 131,
	"feral sphinx": 7082,
	"feral werecrocodile": 408,
	"feverish citizen": 1276,
	"fire devil": 145,
	"fire elemental": 3172,
	"firestarter": 2569,
	"fish": 104,
	"flamingo": 137,
	"flimsy lost soul": 6165,
	"floating savant": 435,
	"flying book": 311,
	"foam stalker": 1875,
	"forest fury": 590,
	"fox": 243,
	"frazzlemaw": 8404,
	"freakish lost soul": 51,
	"frost dragon hatchling": 10,
	"frost dragon": 15,
	"frost flower asura": 941,
	"frost giantess": 57,
	"frost giant": 1,
	"frost troll": 87,
	"fungosaurus": 2,
	"fury": 305,
	"furious fire elemental": 28,
	"furious troll": 16,
	"gang member": 30,
	"gargoyle": 1917,
	"gazer spectre": 3446,
	"gazer": 36,
	"ghastly dragon": 114,
	"ghost wolf": 1154,
	"ghost": 374,
	"ghoul": 1858,
	"giant spider": 348,
	"girtablilu warrior": 2678,
	"gladiator": 69,
	"gloom wolf": 1841,
	"glooth anemone": 227,
	"glooth bandit": 457,
	"glooth battery": 3,
	"glooth blob": 2572,
	"glooth brigand": 438,
	"glooth golem": 2768,
	"gnarlhound": 91,
	"goblin assassin": 29,
	"goblin leader": 16,
	"goblin scavenger": 22,
	"goblin": 110,
	"golden servant": 408,
	"goldhanded cultist": 1,
	"gozzler": 19,
	"grave robber": 17,
	"gravedigger": 2,
	"greater energy elemental": 36,
	"greater fire elemental": 38,
	"green djinn": 44,
	"green frog": 38,
	"grim reaper": 1929,
	"grimeleech": 3569,
	"guardian golem": 12,
	"guardian of tales": 748,
	"guzzlemaw": 3294,
	"hand of cursed fate": 348,
	"hardened usurper archer": 46,
	"hardened usurper knight": 221,
	"hardened usurper warlock": 185,
	"harpy": 1589,
	"haunted treeling": 69,
	"hazardous phantom": 20,
	"hellfire fighter": 274,
	"hellflayer": 992,
	"hellhound": 1033,
	"hellspawn": 4737,
	"hero": 544,
	"hibernal moth": 87,
	"hideous fungus": 136,
	"high voltage elemental": 833,
	"hive overseer": 9,
	"honour guard": 288,
	"hoodinion": 52,
	"horse": 39,
	"hot dog": 1,
	"hulking carnisylvan": 237,
	"humongous fungus": 229,
	"humorless fungus": 156,
	"hunger worm": 13,
	"hunter": 264,
	"husky": 2,
	"hyaena": 873,
	"hydra": 2070,
	"ice golem": 422,
	"ice witch": 123,
	"icecold book": 1412,
	"iks ahpututu": 6,
	"iks aucar": 55,
	"iks chuka": 62,
	"iks churrascan": 32,
	"iks pututu": 41,
	"infected weeper": 7,
	"infernal demon": 6,
	"infernal frog": 3,
	"infernal phantom": 3,
	"ink blob": 7,
	"insane siren": 1352,
	"insect swarm": 186,
	"insectoid scout": 19,
	"insectoid worker": 356,
	"instable breach brood": 37,
	"instable sparkion": 30,
	"iron servant": 504,
	"ironblight": 15,
	"island troll": 14,
	"jellyfish": 133,
	"juggernaut": 112,
	"jungle moa": 118,
	"juvenile bashmu": 1733,
	"killer caiman": 118,
	"killer rabbit": 51,
	"knight familiar": 1,
	"knight's apparition": 301,
	"knowledge elemental": 3813,
	"knowledge raider": 373,
	"kollos": 7,
	"kongra": 1018,
	"lacewing moth": 166,
	"lamassu": 1521,
	"lancer beetle": 671,
	"larva": 543,
	"lava golem": 11,
	"lava lurker attendant": 258,
	"lava lurker": 17,
	"lavafungus": 1626,
	"lavaworm": 1992,
	"leaf golem": 34,
	"lesser magma crystal": 6,
	"lesser swarmer": 247,
	"lich": 210,
	"liodile": 2982,
	"lion archer": 15,
	"lion commander": 26,
	"lion knight": 32,
	"lion warlock": 155,
	"lion": 827,
	"little corym charlatan": 5,
	"lizard chosen": 99,
	"lizard dragon priest": 85,
	"lizard high guard": 202,
	"lizard legionnaire": 81,
	"lizard sentinel": 9,
	"lizard snakecharmer": 2,
	"lizard templar": 5,
	"lizard zaogun": 155,
	"lost berserker": 31,
	"lost exile": 20,
	"lost soul": 616,
	"lumbering carnivor": 1901,
	"mad scientist": 210,
	"mad sheep": 5,
	"magical sphere": 39,
	"Magma Bubble": 11,
	"magma crawler": 15,
	"magma crystal": 33,
	"makara": 321,
	"makeshift home": 7,
	"mammoth": 690,
	"manta ray": 13,
	"manticore": 5477,
	"many faces": 402,
	"marsh stalker": 4511,
	"massive earth elemental": 83,
	"massive fire elemental": 128,
	"massive water elemental": 156,
	"meadow strider": 76,
	"mean lost soul": 2871,
	"mean maw": 5,
	"mean minion": 1,
	"mearidion": 84,
	"mechanical fighter": 16,
	"medusa": 4210,
	"memory of a book": 2,
	"memory of a golem": 2,
	"memory of a hydra": 4,
	"memory of a lizard": 5,
	"menacing carnivor": 932,
	"mercury blob": 175,
	"merlkin": 525,
	"metal gargoyle": 193,
	"midnight asura": 8794,
	"minotaur amazon": 24,
	"minotaur archer": 175,
	"minotaur cult follower": 6459,
	"minotaur cult prophet": 2292,
	"minotaur cult zealot": 1360,
	"minotaur guard": 307,
	"minotaur hunter": 618,
	"minotaur idol": 11,
	"minotaur mage": 112,
	"minotaur": 863,
	"misguided bully": 1116,
	"misguided shadow": 16,
	"misguided thief": 1091,
	"modified gnarlhound": 2,
	"mole": 20,
	"monk": 670,
	"monk of the order": 3,
	"mooh'tah warrior": 1085,
	"moohtant": 17,
	"mould phantom": 132,
	"mountain troll": 415,
	"mummy": 967,
	"murmillion": 171,
	"museum stone golem": 1,
	"museum stone rhino": 1,
	"mushroom sniffer": 24,
	"mutated bat": 848,
	"mutated human": 451,
	"mutated rat": 251,
	"mutated tiger": 281,
	"mycobiontic beetle": 5021,
	"naga archer": 235,
	"naga warrior": 425,
	"necromancer": 181,
	"neutral deepling warrior": 24,
	"nightmare scion": 1107,
	"nightmare": 605,
	"nomad": 198,
	"northern pike": 32,
	"novice of the cult": 524,
	"nymph": 93,
	"ogre brute": 53,
	"ogre rowdy": 2724,
	"ogre ruffian": 1621,
	"ogre sage": 1386,
	"ogre savage": 25,
	"ogre shaman": 32,
	"omnivora": 1421,
	"oozing corpus": 6084,
	"orc berserker": 2957,
	"orc cult fanatic": 186,
	"orc cult inquisitor": 677,
	"orc cult minion": 414,
	"orc cult priest": 385,
	"orc cultist": 398,
	"orc leader": 943,
	"orc marauder": 5,
	"orc rider": 452,
	"orc shaman": 3294,
	"orc spearman": 1006,
	"orc warlord": 355,
	"orc warrior": 1519,
	"orchid frog": 64,
	"orclops doomhauler": 35,
	"orc": 463,
	"orewalker": 15,
	"overcharge": 45,
	"paladin familiar": 8,
	"paladin's apparition": 125,
	"panda": 4,
	"parasite": 26,
	"parder": 137,
	"parrot": 18,
	"party skeleton": 1288,
	"penguin": 188,
	"phantasm": 2881,
	"pigeon": 36,
	"pig": 80,
	"pirat bombardier": 1309,
	"pirat cutthroat": 2216,
	"pirat mate": 1642,
	"pirat scoundrel": 1338,
	"pirate buccaneer": 90,
	"pirate corsair": 44,
	"pirate cutthroat": 139,
	"pirate ghost": 5,
	"pirate marauder": 234,
	"pirate skeleton": 1,
	"pixie": 81,
	"plaguesmith": 959,
	"player": 164,
	"poacher": 280,
	"poison spider": 725,
	"poisonous carnisylvan": 136,
	"polar bear": 215,
	"pooka": 98,
	"priestess": 141,
	"priestess of the wild sun": 387,
	"primal pack beast": 83,
	"putrid mummy": 1565,
	"quara constrictor scout": 764,
	"quara constrictor": 16,
	"quara hydromancer scout": 779,
	"quara hydromancer": 112,
	"quara mantassin scout": 5,
	"quara mantassin": 17,
	"quara pincher scout": 898,
	"quara pincher": 104,
	"quara predator scout": 980,
	"quara predator": 190,
	"rabbit": 192,
	"rage squid": 3185,
	"rat": 172,
	"ravenous lava lurker": 77,
	"reality reaver": 10,
	"reality reavers": 4273,
	"renegade knight": 282,
	"retching horror": 1397,
	"rhindeer": 2360,
	"ripper spectre": 1219,
	"roaring lion": 316,
	"rogue naga": 241,
	"rorc": 217,
	"rot elemental": 1891,
	"rotten golem": 155,
	"rotworm": 530,
	"rustheap golem": 824,
	"salamander": 2437,
	"sand brood": 45,
	"sandcrawler": 1143,
	"scarab": 686,
	"scissorion": 131,
	"scorpion": 1039,
	"sea serpent": 26,
	"seacrest serpent": 15,
	"seagull": 54,
	"security golem": 4,
	"serpent spawn": 3472,
	"servant of Tentugly": 13,
	"shadow pupil": 1,
	"shaper matriarch": 2,
	"shark": 51,
	"sheep": 11,
	"shock head": 153,
	"sibang": 985,
	"silencer": 6484,
	"silver rabbit": 89,
	"skeleton elite warrior": 63,
	"skeleton warrior": 53,
	"skeleton": 1532,
	"skunk": 183,
	"slime": 492,
	"slippery northern pike": 1,
	"slug": 45,
	"smuggler": 719,
	"snake": 1207,
	"solitary frost dragon": 20,
	"son of Verminor": 40,
	"sopping corpus": 3281,
	"sorcerer familiar": 9,
	"sorcerer's apparition": 109,
	"soul reaper": 1,
	"soul-broken harbinger": 740,
	"souleater": 3310,
	"sparkion": 4410,
	"spark of destruction": 529,
	"spectre": 312,
	"sphinx": 4062,
	"spider": 348,
	"spidris": 15,
	"spidris elite": 18,
	"spiky carnivor": 1945,
	"spit nettle": 122,
	"spitter": 28,
	"spyrat": 118,
	"squid warden": 1141,
	"squidgy slime": 160,
	"squirrel": 31,
	"stabilizing dread intruder": 1088,
	"stabilizing reality reaver": 1090,
	"stalker": 164,
	"stampor": 2,
	"stone devourer": 11,
	"stone golem": 1270,
	"stone rhino": 8,
	"stonerefiner": 1795,
	"strange slime": 1,
	"streaked devourer": 1832,
	"sun-marked goanna": 70,
	"swamp troll": 1379,
	"swampling": 2061,
	"swan maiden": 88,
	"swarmer": 286,
	"symbol of fear": 20,
	"tarantula": 1066,
	"tarnished spirit": 7,
	"terramite": 267,
	"terror bird": 41,
	"thanatursus": 1091,
	"The Primal Menace": 4,
	"thornback tortoise": 2462,
	"thornfire wolf": 6,
	"tiger": 21,
	"toad": 702,
	"tormented ghost": 8,
	"tortoise": 1521,
	"toxic swarm": 13,
	"tremendous tyrant": 19,
	"troll champion": 74,
	"troll guard": 22,
	"troll legionnaire": 21,
	"troll-trained salamander": 255,
	"troll": 272,
	"true dawnfire asura": 2200,
	"true frost flower asura": 504,
	"true midnight asura": 2644,
	"tunnel devourer": 14,
	"tunnel tyrant": 929,
	"turbulent elemental": 1466,
	"twisted pooka": 169,
	"twisted shaper": 4,
	"two-headed turtle": 4282,
	"ugly monster": 1,
	"undead dragon": 27,
	"undead gladiator": 1030,
	"unstable spark": 11,
	"usurper archer": 147,
	"usurper commander": 383,
	"usurper knight": 197,
	"usurper warlock": 97,
	"valkyrie": 361,
	"vampire bride": 3,
	"vampire pig": 24,
	"vampire": 317,
	"varnished diremaw": 11,
	"venerable foam stalker": 89,
	"venerable girtablilu": 1196,
	"vermin swarm": 16,
	"vexclaw": 6036,
	"vibrant phantom": 1773,
	"vicious lich": 44,
	"vicious squire": 890,
	"vile destroyer": 36,
	"vile grandmaster": 164,
	"voidshard": 16,
	"vulcongra": 118,
	"wailing widow": 494,
	"walker": 288,
	"walking pillar": 2156,
	"wandering pillar": 713,
	"war golem": 326,
	"war wolf": 1051,
	"warlock": 10,
	"waspoid": 227,
	"wasp": 10354,
	"water buffalo": 5,
	"water elemental": 11,
	"weakened frazzlemaw": 4211,
	"weeper": 16,
	"werebadger": 94,
	"werebear": 60,
	"wereboar": 92,
	"werecrocodile": 899,
	"werefox": 65,
	"werehyaena shaman": 3232,
	"werehyaena": 7825,
	"werelioness": 14586,
	"werelion": 13397,
	"werepanther": 1459,
	"weretiger": 1897,
	"werewolf": 46,
	"white deer": 5,
	"white lion": 4493,
	"white shade": 66,
	"white tiger": 66,
	"white weretiger": 1150,
	"wiggler": 379,
	"wild horse": 4,
	"wild warrior": 228,
	"wilting leaf golem": 237,
	"winter wolf": 1504,
	"wisp": 88,
	"witch": 101,
	"wolf": 664,
	"woodling": 208,
	"worker golem": 645,
	"worm priestess": 761,
	"wyrm": 210,
	"wyvern": 750,
	"yalahari despoiler": 10,
	"yielothax": 2013,
	"young goanna": 11248,
	"young sea serpent": 2,
	"zombie": 39
}
