{
	"Abyssador": 1,
	"Achad": 1,
	"Aftershock": 6,
	"Ahau": 7,
	"Alptramun": 3,
	"Amenef the Burning": 5,
	"Anomaly": 12,
	"Arachir the Ancient One": 1,
	"Ascending Ferumbras": 1,
	"Avalanche": 1,
	"Axeitus Headbanger": 1,
	"Barbaria": 1,
	"Bibby Bloodbath": 12,
	"Black Knight": 3,
	"Black Vixen": 45,
	"Bloodback": 37,
	"Bloodpaw": 1,
	"Bovinus": 1,
	"Brokul": 20,
	"Brother Chill": 1,
	"Brother Freeze": 1,
	"Colerian the Barbarian": 1,
	"Count Vlarkorth": 8,
	"Cublarc the Plunderer": 3,
	"Cursed Gladiator": 1,
	"Custodian": 2,
	"Damage Resonance": 11,
	"Darakan the Executioner": 1,
	"Darkfang": 36,
	"Dazed Leaf Golem": 12,
	"Deathbringer": 1,
	"Deathstrike": 1,
	"Destabilized Ferumbras": 1,
	"Diseased Dan": 1,
	"Drasilla": 1,
	"Drume": 103,
	"Duke Krule": 10,
	"Earl Osam": 8,
	"Ekatrix": 2,
	"Eradicator": 11,
	"Ethershreck": 1,
	"Faceless Bane": 10,
	"Fallen Mooh'Tah Master Ghar": 1,
	"Fazzrah": 1,
	"Ferumbras Soul Splinter": 8,
	"Foreman Kneebiter": 1,
	"Foreshock": 6,
	"Frostfur": 1,
	"Fugue": 1,
	"Gaffir": 7,
	"Ghulosh": 4,
	"Glitterscale": 1,
	"Gnomevil": 1,
	"Gnorre Chyllson": 1,
	"Gorgo": 1,
	"Gorzindel": 4,
	"Goshnar's Cruelty": 1,
	"Goshnar's Hatred": 6,
	"Goshnar's Spite": 1,
	"Grand Canon Dominus": 62,
	"Grand Chaplain Gaunder": 35,
	"Grand Commander Soeren": 51,
	"Grand Master Oberon": 92,
	"Grandfather Tridian": 1,
	"Grimgor Guteater": 1,
	"Guard Captain Quaid": 9,
	"Heoni": 34,
	"Inky": 1,
	"Irgix the Flimsy": 6,
	"Izcandar Champion of Summer": 1,
	"Izcandar Champion of Winter": 1,
	"Izcandar the Banished": 1,
	"Jailer": 105,
	"Katex Blood Tongue": 44,
	"King Zelos": 1,
	"Koshei the Deathless": 1,
	"Kraknaknork": 1,
	"Kreebosh the Exile": 1,
	"Kroazur": 11,
	"Kusuma": 12,
	"Lady Tenebris": 3,
	"Leiden": 4,
	"Lloyd": 2,
	"Lokathmor": 1,
	"Lord Azaram": 8,
	"Mad Mage": 1,
	"Mazzinor": 4,
	"Megasylvan Yselda": 2,
	"Neferi the Spy": 5,
	"Norgle Glacierbeard": 1,
	"Orcus the Cruel": 1,
	"Outburst": 12,
	"Owin": 2,
	"Preceptor Lazare": 56,
	"Raging Mage": 1,
	"Ratmiral Blackwhiskers": 3,
	"Ravenous Hunger": 4,
	"Realityquake": 6,
	"Rocky": 1,
	"Rupture": 2,
	"Scarlett Etzel": 166,
	"Shadowpelt": 39,
	"Shard of Corruption": 1,
	"Sharpclaw": 37,
	"Sharptooth": 1,
	"Sir Baeloc": 9,
	"Sir Nictros": 9,
	"Sir Valorcrest": 1,
	"Sister Hetai": 4,
	"Slim": 1,
	"Soul of Dragonking Zyrtarch": 1,
	"Spirits of Earth": 1,
	"Spirits of Fire": 1,
	"Spirits of Water": 1,
	"Splasher": 1,
	"Srezz Yellow Eyes": 44,
	"Sulphur Scuttler": 2,
	"Svoren the Mad": 1,
	"Thawing Dragon Lord": 4,
	"The Blazing Rose": 1,
	"The Brainstealer": 9,
	"The Count of the Core": 3,
	"The Dark Dancer": 1,
	"The Diamond Blossom": 1,
	"The Dread Maiden": 1,
	"The End of Days": 60,
	"The Enraged Thorn Knight": 1,
	"The Fear Feaster": 2,
	"The Flaming Orchid": 6,
	"The Hag": 1,
	"The Hairy One": 1,
	"The Lily of Night": 1,
	"The Many": 1,
	"The Masked Marauder": 1,
	"The Monster": 10,
	"The Moonlight Aster": 6,
	"The Nightmare Beast": 1,
	"The Obliverator": 1,
	"The Old Whopper": 1,
	"The Pale Worm": 3,
	"The Pit Lord": 1,
	"The Scourge of Oblivion": 1,
	"The Spellstealer": 1,
	"The Time Guardian": 1,
	"The Weakened Count": 1,
	"The Winter Bloom": 6,
	"Timira the Many-Headed": 73,
	"Unaz the Mean": 7,
	"Ungreez": 1,
	"Urmahlullu the Weakened": 7,
	"Utua Stone Sting": 43,
	"Versperoth": 1,
	"Vok the Freakish": 7,
	"Webster": 1,
	"Xogixath": 1,
	"Yirkas Blue Scales": 44,
	"Zevelon Duskbringer": 1,
	"abyssal calamary": 8,
	"acid blob": 56,
	"acolyte of the cult": 1157,
	"adept of the cult": 2701,
	"adult goanna": 3752,
	"adventurer": 44,
	"afflicted strider": 53,
	"amazon": 1813,
	"ancient lion knight": 49,
	"ancient scarab": 170,
	"angry adventurer": 1,
	"animated feather": 1346,
	"arachnophobica": 5639,
	"arctic faun": 37,
	"armadile": 12,
	"assassin": 86,
	"azure frog": 53,
	"badger": 977,
	"bandit": 90,
	"banshee": 35,
	"barbarian bloodwalker": 125,
	"barbarian brutetamer": 167,
	"barbarian headsplitter": 361,
	"barbarian skullhunter": 308,
	"barkless devotee": 354,
	"barkless fanatic": 286,
	"bashmu": 2556,
	"bat": 958,
	"bear": 166,
	"behemoth": 363,
	"berserker chicken": 59,
	"betrayed wraith": 636,
	"biting book": 662,
	"black cobra": 13,
	"black sheep": 2,
	"black sphinx acolyte": 445,
	"blemished spawn": 111,
	"blightwalker": 61,
	"blood beast": 1209,
	"blood crab": 151,
	"blood hand": 8,
	"blood priest": 133,
	"blue djinn": 30,
	"boar man": 3908,
	"boar": 32,
	"bog frog": 114,
	"bog raider": 102,
	"bonebeast": 981,
	"bonelord": 622,
	"bony sea devil": 2679,
	"boogy": 262,
	"brain squid": 4690,
	"braindeath": 89,
	"branchy crawler": 5130,
	"breach brood": 8220,
	"brimstone bug": 1949,
	"brittle skeleton": 38,
	"broken shaper": 11,
	"bug": 571,
	"burning book": 2577,
	"burning gladiator": 1244,
	"burster spectre": 8442,
	"butterfly": 104,
	"calamary": 35,
	"capricious phantom": 1849,
	"carniphila": 143,
	"carnisylvan sapling": 59,
	"carnivostrich": 2784,
	"carrion worm": 113,
	"cat": 35,
	"cave chimera": 62,
	"cave devourer": 4,
	"cave hydra": 18,
	"cave parrot": 14,
	"cave rat": 587,
	"centipede": 311,
	"chakoya toolshaper": 114,
	"chakoya tribewarden": 136,
	"chakoya windcaller": 74,
	"charger": 744,
	"charging Outburst": 46,
	"chicken": 183,
	"choking fear": 411,
	"clay guardian": 86,
	"cliff strider": 10,
	"cloak of terror": 1285,
	"clomp": 523,
	"cobra assassin": 5828,
	"cobra scout": 3165,
	"cobra vizier": 1425,
	"cobra": 559,
	"coral frog": 36,
	"corrupt naga": 305,
	"corrupted soul": 87,
	"corym charlatan": 751,
	"corym skirmisher": 595,
	"corym vanguard": 125,
	"cosmic energy prism A": 2,
	"cosmic energy prism B": 2,
	"cosmic energy prism C": 2,
	"cosmic energy prism D": 2,
	"courage leech": 679,
	"crab": 260,
	"crape man": 1107,
	"crawler": 1125,
	"crazed beggar": 20,
	"crazed summer rearguard": 5858,
	"crazed summer vanguard": 5073,
	"crazed winter rearguard": 806,
	"crazed winter vanguard": 780,
	"crimson frog": 59,
	"crocodile": 414,
	"crypt shambler": 1067,
	"crypt warden": 3233,
	"crystal spider": 31,
	"crystal wolf": 7,
	"crystalcrusher": 425,
	"cult believer": 1211,
	"cult enforcer": 527,
	"cult scholar": 289,
	"cursed ape": 38,
	"cyclops": 984,
	"cyclops drone": 241,
	"cyclops smith": 160,
	"damaged worker golem": 38,
	"dark apprentice": 403,
	"dark carnisylvan": 98,
	"dark faun": 608,
	"dark magician": 283,
	"dark monk": 56,
	"dark torturer": 1175,
	"dawn bat": 6,
	"dawnfire asura": 8779,
	"dawnfly": 72,
	"death blob": 1274,
	"deathling scout": 715,
	"deathling spellsinger": 339,
	"deepling elite": 24,
	"deepling guard": 674,
	"deepling master librarian": 22,
	"deepling scout": 162,
	"deepling spellsinger": 874,
	"deepling tyrant": 81,
	"deepling warrior": 695,
	"deepsea blood crab": 40,
	"deepworm": 1308,
	"deer": 119,
	"demon outcast": 522,
	"demon skeleton": 801,
	"demon": 438,
	"depolarized crackler": 24,
	"desperate white deer": 50,
	"destroyer": 28,
	"devourer": 1165,
	"diamond servant replica": 632,
	"diamond servant": 64,
	"diremaw": 3035,
	"dog": 66,
	"domestikion": 11,
	"dragon hatchling": 380,
	"dragon lord hatchling": 31,
	"dragon lord": 298,
	"dragon servant": 77,
	"dragon wrath": 2,
	"dragon": 884,
	"draken abomination": 464,
	"draken elite": 327,
	"draken spellweaver": 1769,
	"draken warmaster": 2016,
	"dread intruder": 7316,
	"drillworm": 225,
	"dromedary": 77,
	"dryad": 230,
	"dwarf geomancer": 3,
	"dwarf guard": 155,
	"dwarf soldier": 383,
	"dwarf": 392,
	"dworc fleshhunter": 7,
	"dworc venomsniper": 1,
	"dworc voodoomaster": 10,
	"earth elemental": 223,
	"efreet": 14,
	"elder bonelord": 136,
	"elder wyrm": 318,
	"elephant": 100,
	"elf arcanist": 286,
	"elf scout": 1015,
	"elf": 867,
	"emerald damselfly": 2198,
	"energetic book": 4149,
	"energized raging mage": 6,
	"energuardian of tales": 2873,
	"energy elemental": 157,
	"enfeebled silencer": 1592,
	"enlightened of the cult": 1782,
	"enraged bookworm": 25,
	"enraged crystal golem": 64,
	"enraged squirrel": 4,
	"enraged white deer": 6,
	"enslaved dwarf": 14,
	"enthralled demon": 63,
	"eternal guardian": 1763,
	"execowtioner": 21,
	"exotic bat": 6012,
	"exotic cave spider": 2351,
	"eyeless devourer": 73,
	"falcon knight": 1528,
	"falcon paladin": 1016,
	"faun": 2,
	"feral sphinx": 3390,
	"feverish citizen": 2831,
	"feversleep": 5,
	"fire devil": 68,
	"fire elemental": 1250,
	"firestarter": 1852,
	"fish": 76,
	"flamingo": 184,
	"flimsy lost soul": 7190,
	"floating savant": 75,
	"flying book": 337,
	"foam stalker": 1484,
	"forest fury": 2117,
	"fox": 883,
	"frazzlemaw": 4959,
	"freakish lost soul": 136,
	"frost dragon hatchling": 308,
	"frost dragon": 391,
	"frost flower asura": 2047,
	"frost giantess": 26,
	"frost giant": 35,
	"frost troll": 151,
	"fungosaurus": 4,
	"fury": 83,
	"gang member": 13,
	"gargoyle": 520,
	"gazer spectre": 7604,
	"gazer": 218,
	"ghastly dragon": 1,
	"ghost wolf": 798,
	"ghost": 590,
	"ghoulish hyaena": 6,
	"ghoul": 2435,
	"giant spider": 140,
	"girtablilu warrior": 653,
	"gloom wolf": 3137,
	"glooth anemone": 400,
	"glooth bandit": 398,
	"glooth blob": 2557,
	"glooth brigand": 412,
	"glooth golem": 358,
	"gnarlhound": 115,
	"gnome pack crawler": 1,
	"goblin assassin": 112,
	"goblin leader": 7,
	"goblin scavenger": 205,
	"goblin": 687,
	"golden servant replica": 628,
	"golden servant": 200,
	"gozzler": 35,
	"gravedigger": 3,
	"greater energy elemental": 14,
	"greater fire elemental": 18,
	"green djinn": 30,
	"green frog": 36,
	"grim reaper": 452,
	"grimeleech": 840,
	"guardian golem": 12,
	"guardian of tales": 640,
	"guzzlemaw": 771,
	"hand of cursed fate": 202,
	"hardened usurper archer": 59,
	"hardened usurper knight": 176,
	"hardened usurper warlock": 179,
	"harpy": 715,
	"haunted treeling": 110,
	"hazardous phantom": 67,
	"headpecker": 1864,
	"hellfire fighter": 103,
	"hellflayer": 51,
	"hellhound": 759,
	"hellspawn": 2937,
	"hero": 1559,
	"hibernal moth": 66,
	"hideous fungus": 96,
	"high voltage elemental": 15,
	"hive overseer": 13,
	"hoodinion": 7,
	"hulking carnisylvan": 137,
	"humongous fungus": 248,
	"humorless fungus": 158,
	"hunger worm": 9,
	"hunter": 53,
	"husky": 48,
	"hyaena": 490,
	"hydra": 1594,
	"ice golem": 74,
	"ice witch": 18,
	"icecold book": 1529,
	"iks ahpututu": 2,
	"iks aucar": 22,
	"iks chuka": 30,
	"iks churrascan": 10,
	"iks pututu": 24,
	"infected weeper": 5,
	"ink blob": 80,
	"insane siren": 2070,
	"insect swarm": 78,
	"insectoid worker": 1052,
	"instable breach brood": 392,
	"instable sparkion": 140,
	"iron servant replica": 809,
	"iron servant": 244,
	"ironblight": 16,
	"island troll": 30,
	"jellyfish": 177,
	"juggernaut": 43,
	"jungle moa": 48,
	"juvenile bashmu": 3829,
	"killer caiman": 208,
	"knight familiar": 2,
	"knowledge elemental": 3043,
	"knowledge raider": 173,
	"kollos": 63,
	"kongra": 1672,
	"lacewing moth": 247,
	"lamassu": 1201,
	"lancer beetle": 806,
	"larva": 171,
	"lava golem": 24,
	"lava lurker attendant": 59,
	"lavafungus": 657,
	"lavaworm": 788,
	"leaf golem": 159,
	"lesser fire devil": 1,
	"lesser magma crystal": 3,
	"lesser swarmer": 185,
	"lich": 85,
	"liodile": 3691,
	"lion archer": 41,
	"lion commander": 27,
	"lion knight": 20,
	"lion warlock": 273,
	"lion": 525,
	"little corym charlatan": 11,
	"lizard chosen": 10,
	"lizard dragon priest": 91,
	"lizard high guard": 335,
	"lizard legionnaire": 256,
	"lizard sentinel": 65,
	"lizard snakecharmer": 52,
	"lizard templar": 50,
	"lizard zaogun": 89,
	"lost basher": 64,
	"lost berserker": 28,
	"lost exile": 11,
	"lost gnome": 3,
	"lost husher": 47,
	"lost soul": 536,
	"lost thrower": 75,
	"lost time": 15,
	"lumbering carnivor": 5098,
	"mad scientist": 64,
	"mad sheep": 1,
	"magical sphere": 63,
	"Magma Bubble": 9,
	"magma crawler": 21,
	"magma crystal": 30,
	"makara": 712,
	"makeshift home": 6,
	"mammoth": 584,
	"manta ray": 161,
	"manticore": 2382,
	"mantosaurus": 2025,
	"marsh stalker": 1064,
	"massive earth elemental": 110,
	"massive fire elemental": 42,
	"massive water elemental": 22,
	"meadow strider": 96,
	"mean lost soul": 2727,
	"mean maw": 15,
	"mearidion": 19,
	"medusa": 2835,
	"menacing carnivor": 1542,
	"mercurial menace": 752,
	"mercury blob": 58,
	"merlkin": 825,
	"midnight asura": 8681,
	"minotaur amazon": 13,
	"minotaur archer": 372,
	"minotaur cult follower": 3555,
	"minotaur cult prophet": 1285,
	"minotaur cult zealot": 829,
	"minotaur guard": 627,
	"minotaur hunter": 329,
	"minotaur mage": 250,
	"minotaur": 1323,
	"modified gnarlhound": 88,
	"mole": 26,
	"monk": 399,
	"mooh'tah warrior": 283,
	"moohtant": 15,
	"mould phantom": 2341,
	"mountain troll": 468,
	"muglex clan assassin": 1,
	"muglex clan feetman": 11,
	"muglex clan scavenger": 2,
	"mummy": 924,
	"murmillion": 21,
	"mushroom sniffer": 19,
	"mutated bat": 425,
	"mutated human": 177,
	"mutated rat": 104,
	"mutated tiger": 45,
	"naga archer": 471,
	"naga warrior": 880,
	"necromancer": 152,
	"neutral deepling warrior": 27,
	"nightmare scion": 53,
	"nightmare": 148,
	"nightstalker": 1,
	"noble lion": 54,
	"nomad": 252,
	"northern pike": 25,
	"novice of the cult": 447,
	"noxious ripptor": 2009,
	"nymph": 17,
	"ogre brute": 27,
	"ogre rowdy": 955,
	"ogre ruffian": 614,
	"ogre sage": 461,
	"ogre savage": 10,
	"ogre shaman": 17,
	"omnivora": 111,
	"orc berserker": 2064,
	"orc cult fanatic": 7,
	"orc cult inquisitor": 11,
	"orc cult minion": 18,
	"orc cult priest": 3,
	"orc leader": 712,
	"orc marauder": 208,
	"orc rider": 334,
	"orc shaman": 3144,
	"orc spearman": 806,
	"orc warlord": 275,
	"orc warrior": 1388,
	"orchid frog": 35,
	"orclops doomhauler": 56,
	"orclops ravager": 37,
	"orc": 539,
	"orewalker": 15,
	"overcharge": 81,
	"panda": 5,
	"parasite": 13,
	"parder": 86,
	"parrot": 19,
	"party skeleton": 1383,
	"penguin": 276,
	"phantasm": 691,
	"pigeon": 88,
	"pig": 185,
	"pirat bombardier": 3743,
	"pirat cutthroat": 7612,
	"pirat mate": 3049,
	"pirat scoundrel": 3535,
	"pirate buccaneer": 170,
	"pirate corsair": 54,
	"pirate cutthroat": 283,
	"pirate ghost": 4,
	"pirate marauder": 667,
	"pirate skeleton": 15,
	"pixie": 17,
	"plaguesmith": 257,
	"player": 16,
	"poacher": 116,
	"poison spider": 1015,
	"poisonous carnisylvan": 145,
	"polar bear": 221,
	"possessed tree": 10,
	"priestess": 36,
	"priestess of the wild sun": 954,
	"primal pack beast": 19,
	"putrid mummy": 2621,
	"quara constrictor scout": 198,
	"quara constrictor": 356,
	"quara hydromancer scout": 217,
	"quara hydromancer": 209,
	"quara mantassin scout": 17,
	"quara mantassin": 308,
	"quara pincher scout": 216,
	"quara pincher": 308,
	"quara predator scout": 264,
	"quara predator": 253,
	"rabbit": 246,
	"rage squid": 2436,
	"rat": 480,
	"ravenous lava lurker": 1016,
	"reality reaver": 68,
	"reality reavers": 8262,
	"redeemed soul": 20,
	"reflection of a Mage": 1,
	"renegade knight": 1132,
	"retching horror": 589,
	"rhindeer": 1143,
	"rift invader": 140,
	"ripper spectre": 1991,
	"roaring lion": 874,
	"rogue naga": 303,
	"rorc": 132,
	"rot elemental": 1456,
	"rotten golem": 3131,
	"rotworm": 795,
	"rustheap golem": 380,
	"salamander": 769,
	"sandcrawler": 610,
	"scarab": 16,
	"scissorion": 22,
	"scorpion": 661,
	"sea serpent": 58,
	"seacrest serpent": 109,
	"seagull": 48,
	"serpent spawn": 2278,
	"servant of Tentugly": 9,
	"shadow fiend": 197,
	"shadow pupil": 5,
	"shadow tentacle": 15,
	"shaper matriarch": 1,
	"shark": 126,
	"sheep": 42,
	"shock head": 279,
	"shrieking cry-stal": 742,
	"sibang": 1834,
	"sight of surrender": 5,
	"silencer": 3162,
	"silver rabbit": 66,
	"skeleton elite warrior": 78,
	"skeleton warrior": 85,
	"skeleton": 1072,
	"skunk": 101,
	"slime": 211,
	"slug": 14,
	"smuggler": 243,
	"snake": 1567,
	"solitary frost dragon": 6,
	"soul-broken harbinger": 408,
	"souleater": 2039,
	"sparkion": 8257,
	"spark of destruction": 1064,
	"sphinx": 5175,
	"spider": 506,
	"spidris": 187,
	"spidris elite": 55,
	"spiky carnivor": 8279,
	"spit nettle": 68,
	"spitter": 397,
	"spyrat": 118,
	"squid warden": 1298,
	"squidgy slime": 80,
	"squirrel": 145,
	"stalker": 38,
	"starving wolf": 86,
	"stone devourer": 9,
	"stone golem": 99,
	"stonerefiner": 1292,
	"strange rat": 16,
	"streaked devourer": 762,
	"sun-marked goanna": 26,
	"swamp troll": 1673,
	"swampling": 1080,
	"swan maiden": 23,
	"swarmer hatchling": 2,
	"swarmer": 1022,
	"symbol of fear": 10,
	"symbol of hatred": 155,
	"tainted soul": 113,
	"tarantula": 483,
	"tarnished spirit": 52,
	"terramite": 106,
	"terror bird": 39,
	"terrorsleep": 10,
	"thanatursus": 1740,
	"The Primal Menace": 1,
	"thieving squirrel": 1,
	"thorn minion": 74,
	"thorn steed": 1,
	"thornback tortoise": 596,
	"thornfire wolf": 8,
	"tiger": 50,
	"time keeper": 48,
	"toad": 452,
	"tomb servant": 40,
	"tortoise": 767,
	"toxic swarm": 32,
	"tremendous tyrant": 39,
	"troll champion": 126,
	"troll-trained salamander": 193,
	"troll": 477,
	"true dawnfire asura": 2161,
	"true frost flower asura": 559,
	"true midnight asura": 2571,
	"tunnel devourer": 9,
	"tunnel tyrant": 19,
	"turbulent elemental": 3080,
	"twisted pooka": 529,
	"twisted shaper": 12,
	"two-headed turtle": 3447,
	"ugly monster": 5,
	"unbound blightwalker": 2,
	"unbound demon outcast": 2,
	"unbound demon": 6,
	"undead cavebear": 1,
	"undead gladiator": 330,
	"undead mine worker": 4,
	"undead prospector": 2,
	"unstable spark": 68,
	"usurper archer": 2,
	"usurper commander": 309,
	"usurper knight": 10,
	"usurper warlock": 5,
	"valkyrie": 843,
	"vampire bride": 401,
	"vampire viscount": 400,
	"vampire": 646,
	"varnished diremaw": 61,
	"venerable foam stalker": 75,
	"venerable girtablilu": 272,
	"vexclaw": 566,
	"vibrant phantom": 493,
	"vicious lich": 14,
	"vicious squire": 2767,
	"vile destroyer": 12,
	"vile grandmaster": 673,
	"vulcongra": 128,
	"wailing widow": 459,
	"war golem": 101,
	"war wolf": 1855,
	"warlock": 1,
	"waspoid": 869,
	"wasp": 791,
	"water buffalo": 30,
	"water elemental": 12,
	"weakened frazzlemaw": 2660,
	"weeper": 17,
	"werebadger": 547,
	"werebear": 334,
	"wereboar": 397,
	"werefox": 542,
	"werehyaena shaman": 2417,
	"werehyaena": 6391,
	"werelioness": 18143,
	"werelion": 16396,
	"werewolf": 173,
	"white deer": 61,
	"white lion": 5754,
	"white shade": 64,
	"wiggler": 333,
	"wild warrior": 58,
	"wilting leaf golem": 291,
	"winter wolf": 651,
	"wisp": 53,
	"witch": 224,
	"wolf": 582,
	"woodling": 161,
	"worker golem": 139,
	"worm priestess": 369,
	"wyrm": 2234,
	"wyvern": 1510,
	"yalahari despoiler": 15,
	"yielothax": 769,
	"young goanna": 4915,
	"young sea serpent": 19,
	"zombie": 94
}
