{
	"agrestic chicken": 242969,
	"parrot": 455306,
	"white deer": 498913,
	"fish": 506312,
	"black sheep": 532249,
	"cave parrot": 588685,
	"wisp": 665404,
	"bog frog": 754953,
	"horse": 910468,
	"sheep": 954064,
	"skunk": 1202671,
	"green frog": 1286841,
	"dromedary": 1352720,
	"silver rabbit": 1367677,
	"seagull": 1440630,
	"flamingo": 1451677,
	"squirrel": 1500791,
	"frost troll": 1814005,
	"pig": 2020822,
	"island troll": 2655906,
	"deer": 2778435,
	"rabbit": 2878671,
	"goblin": 3296605,
	"chicken": 3595532,
	"penguin": 3733099,
	"rat": 4350992,
	"cave rat": 5793813,
	"spider": 6276801,
	"bug": 6429641,
	"troll": 6696536,
	"winter wolf": 7503571,
	"sandcrawler": 8418788,
	"bat": 11568616,
	"wolf": 11686785,
	"fox": 12353727,
	"snake": 12883158,
	"badger": 15378795,
	"poison spider": 16267885,
	"wasp": 19610002
}
