{
	"yeti": 637,
	"midnight panther": 1151,
	"crustacea gigantica": 4002,
	"dire penguin": 4402,
	"elf overseer": 7057,
	"raging fire": 7153,
	"draptor": 7155,
	"undead cavebear": 8532,
	"crystal wolf": 10420,
	"thornfire wolf": 10694,
	"vicious manbat": 12111,
	"wild horse": 22992,
	"berrypest": 24268,
	"nightfiend": 27864,
	"troll guard": 28033,
	"goblin leader": 71161,
	"midnight spawn": 157047,
	"iks ahpututu": 157975,
	"shadow hound": 158538,
	"nightslayer": 169821,
	"acolyte of darkness": 170118,
	"herald of gloom": 171288,
	"bane of light": 172096,
	"midnight warrior": 185572,
	"doomsday cultist": 201734,
	"duskbringer": 222603,
	"water buffalo": 252932,
	"bride of night": 383609,
	"diamond servant": 874047,
	"golden servant": 2960924,
	"iron servant": 3643260
}
